MultiBars/__init__.py
MultiBars/__main__.py
MultiBars/progress.py
multi_bars-0.1.0.dist-info/METADATA
multi_bars-0.1.0.dist-info/WHEEL
multi_bars-0.1.0.dist-info/top_level.txt
multi_bars-0.1.0.dist-info/RECORD
