Metadata-Version: 2.1
Name: multi_bars
Version: 0.1.0
Summary: MultiBars is a simple package for progress bar
Author: DiamondGotCat
Author-email: chii@kamu.jp
Classifier: Programming Language :: Python :: 3
Classifier: License :: OSI Approved :: MIT License
Classifier: Operating System :: OS Independent
Requires-Python: >=3.6
